MANIFEST.in
setup.py
google/ads/searchads360/__init__.py
google/ads/searchads360/v0/__init__.py
google/ads/searchads360/v0/gapic_version.py
google/ads/searchads360/v0/common/__init__.py
google/ads/searchads360/v0/common/gapic_version.py
google/ads/searchads360/v0/common/services/__init__.py
google/ads/searchads360/v0/common/types/__init__.py
google/ads/searchads360/v0/common/types/ad_asset.py
google/ads/searchads360/v0/common/types/ad_type_infos.py
google/ads/searchads360/v0/common/types/asset_types.py
google/ads/searchads360/v0/common/types/asset_usage.py
google/ads/searchads360/v0/common/types/bidding.py
google/ads/searchads360/v0/common/types/criteria.py
google/ads/searchads360/v0/common/types/custom_parameter.py
google/ads/searchads360/v0/common/types/frequency_cap.py
google/ads/searchads360/v0/common/types/metrics.py
google/ads/searchads360/v0/common/types/real_time_bidding_setting.py
google/ads/searchads360/v0/common/types/segments.py
google/ads/searchads360/v0/common/types/targeting_setting.py
google/ads/searchads360/v0/common/types/text_label.py
google/ads/searchads360/v0/common/types/value.py
google/ads/searchads360/v0/enums/__init__.py
google/ads/searchads360/v0/enums/gapic_version.py
google/ads/searchads360/v0/enums/services/__init__.py
google/ads/searchads360/v0/enums/types/__init__.py
google/ads/searchads360/v0/enums/types/account_status.py
google/ads/searchads360/v0/enums/types/account_type.py
google/ads/searchads360/v0/enums/types/ad_group_ad_engine_status.py
google/ads/searchads360/v0/enums/types/ad_group_ad_rotation_mode.py
google/ads/searchads360/v0/enums/types/ad_group_ad_status.py
google/ads/searchads360/v0/enums/types/ad_group_criterion_engine_status.py
google/ads/searchads360/v0/enums/types/ad_group_criterion_status.py
google/ads/searchads360/v0/enums/types/ad_group_engine_status.py
google/ads/searchads360/v0/enums/types/ad_group_status.py
google/ads/searchads360/v0/enums/types/ad_group_type.py
google_ads_searchads360.egg-info/PKG-INFO
google_ads_searchads360.egg-info/SOURCES.txt
google_ads_searchads360.egg-info/dependency_links.txt
google_ads_searchads360.egg-info/not-zip-safe
google_ads_searchads360.egg-info/requires.txt
google_ads_searchads360.egg-info/top_level.txt
